pysocialforce/__init__.py
pysocialforce/fieldofview.py
pysocialforce/forces.py
pysocialforce/potentials.py
pysocialforce/scene.py
pysocialforce/simulator.py
pysocialforce/config/default.toml
pysocialforce/utils/__init__.py
pysocialforce/utils/config.py
pysocialforce/utils/logging.py
pysocialforce/utils/plot.py
pysocialforce/utils/stateutils.py
PySocialForce-1.1.2.dist-info/LICENSE
PySocialForce-1.1.2.dist-info/METADATA
PySocialForce-1.1.2.dist-info/WHEEL
PySocialForce-1.1.2.dist-info/top_level.txt
PySocialForce-1.1.2.dist-info/RECORD
