Metadata-Version: 2.1
Name: PySocialForce
Version: 1.1.2
Summary: Numpy implementation of the Extended Social Force model.
Home-page: https://github.com/yuxiang-gao/PySocialForce
Author: Yuxiang Gao
Author-email: yuxiang.gao@jhu.edu
License: MIT
Platform: UNKNOWN
Classifier: Development Status :: 4 - Beta
Classifier: Intended Audience :: Developers
Classifier: Natural Language :: English
Classifier: License :: OSI Approved :: MIT License
Classifier: Operating System :: OS Independent
Classifier: Programming Language :: Python
Classifier: Programming Language :: Python :: 3.7
Classifier: Programming Language :: Python :: 3.8
Requires-Dist: numpy (>=1.19)
Requires-Dist: toml (>=0.10)
Requires-Dist: numba (>=0.51)
Requires-Dist: scipy (>=1.5)
Provides-Extra: dev
Requires-Dist: black ; extra == 'dev'
Requires-Dist: jupyter ; extra == 'dev'
Provides-Extra: plot
Requires-Dist: matplotlib ; extra == 'plot'
Provides-Extra: test
Requires-Dist: pylint ; extra == 'test'
Requires-Dist: pytest ; extra == 'test'
